Metadata-Version: 1.0
Name: bubbly
Version: 1.0.2
Summary: A module for plotting interactive and animated bubble charts using Plotly
Home-page: https://github.com/AashitaK/bubbly
Author: Aashita Kesarwani
Author-email: kesar01@gmail.com
License: MIT
Keywords: Plotly,bubble charts,animated graphs,interactive graphs
Platform: UNKNOWN
